LICENSE
README.md
setup.cfg
setup.py
terran/__init__.py
terran/checkpoint.py
terran/cli.py
terran/defaults.py
terran.egg-info/PKG-INFO
terran.egg-info/SOURCES.txt
terran.egg-info/dependency_links.txt
terran.egg-info/entry_points.txt
terran.egg-info/requires.txt
terran.egg-info/top_level.txt
terran/face/__init__.py
terran/face/detection/__init__.py
terran/face/detection/retinaface/__init__.py
terran/face/detection/retinaface/anchors.py
terran/face/detection/retinaface/model.py
terran/face/detection/retinaface/wrapper.py
terran/face/recognition/__init__.py
terran/face/recognition/arcface/__init__.py
terran/face/recognition/arcface/model.py
terran/face/recognition/arcface/wrapper.py
terran/io/__init__.py
terran/io/image.py
terran/io/video/__init__.py
terran/io/video/reader.py
terran/io/video/writer.py
terran/pose/__init__.py
terran/pose/openpose/__init__.py
terran/pose/openpose/model.py
terran/pose/openpose/wrapper.py
terran/tracking/__init__.py
terran/tracking/face.py
terran/vis/__init__.py
terran/vis/cairo.py
terran/vis/pillow.py